LICENSE
MANIFEST.in
README.md
donut.py
setup.py
donut.egg-info/PKG-INFO
donut.egg-info/SOURCES.txt
donut.egg-info/dependency_links.txt
donut.egg-info/entry_points.txt
donut.egg-info/top_level.txt