Metadata-Version: 1.1
Name: donut
Version: 0.2.1
Summary: Makes symlinks to dotfiles.
Home-page: https://github.com/lukeolson/donut
Author: Luke Olson
Author-email: luke.olson@gmail.com
License: MIT
Platform: UNKNOWN
Classifier: Environment :: Console
Classifier: License :: OSI Approved :: MIT License
Classifier: Programming Language :: Python
Classifier: Programming Language :: Python :: 2
Classifier: Programming Language :: Python :: 3
Classifier: Topic :: Utilities
